{"DocumentConnection":{"type":"DocumentConnection","resolveType":"multiCollectionDocumentList","collections":["posts_ua","posts_en","pages_ua","pages_en"]},"Node":{"type":"Node","resolveType":"nodeDocument"},"DocumentNode":{"type":"DocumentNode","resolveType":"multiCollectionDocument","createDocument":"create","updateDocument":"update"},"Posts_ua":{"type":"Posts_ua","resolveType":"collectionDocument","collection":"posts_ua","createPosts_ua":"create","updatePosts_ua":"update"},"Posts_uaConnection":{"type":"Posts_uaConnection","resolveType":"collectionDocumentList","collection":"posts_ua"},"Posts_en":{"type":"Posts_en","resolveType":"collectionDocument","collection":"posts_en","createPosts_en":"create","updatePosts_en":"update"},"Posts_enConnection":{"type":"Posts_enConnection","resolveType":"collectionDocumentList","collection":"posts_en"},"Pages_ua":{"type":"Pages_ua","resolveType":"collectionDocument","collection":"pages_ua","createPages_ua":"create","updatePages_ua":"update"},"Pages_uaConnection":{"type":"Pages_uaConnection","resolveType":"collectionDocumentList","collection":"pages_ua"},"Pages_en":{"type":"Pages_en","resolveType":"collectionDocument","collection":"pages_en","createPages_en":"create","updatePages_en":"update"},"Pages_enConnection":{"type":"Pages_enConnection","resolveType":"collectionDocumentList","collection":"pages_en"}}